biokit/__init__.py
biokit/__main__.py
biokit/biokit.py
biokit/version.py
biokit/adapters/NexteraPE-PE.txt
biokit/adapters/TruSeq2-PE.txt
biokit/adapters/TruSeq2-SE.txt
biokit/adapters/TruSeq3-PE-2.txt
biokit/adapters/TruSeq3-PE.txt
biokit/adapters/TruSeq3-SE.txt
biokit/helpers/__init__.py
biokit/helpers/boolean_argument_parsing.py
biokit/helpers/calculate_character_frequencies.py
biokit/helpers/files.py
biokit/helpers/stats_summary.py
biokit/recoding_tables/Dayhoff-12.txt
biokit/recoding_tables/Dayhoff-15.txt
biokit/recoding_tables/Dayhoff-18.txt
biokit/recoding_tables/Dayhoff-6.txt
biokit/recoding_tables/Dayhoff-9.txt
biokit/recoding_tables/KGB-6.txt
biokit/recoding_tables/RY-nucleotide.txt
biokit/recoding_tables/S_and_R-6.txt
biokit/services/__init__.py
biokit/services/base.py
biokit/services/alignment/__init__.py
biokit/services/alignment/alignment_length.py
biokit/services/alignment/alignment_recoding.py
biokit/services/alignment/alignment_summary.py
biokit/services/alignment/base.py
biokit/services/alignment/consensus_sequence.py
biokit/services/alignment/constant_sites.py
biokit/services/alignment/faidx.py
biokit/services/alignment/parsimony_informative_sites.py
biokit/services/alignment/position_specific_score_matrix.py
biokit/services/alignment/variable_sites.py
biokit/services/coding_sequences/__init__.py
biokit/services/coding_sequences/base.py
biokit/services/coding_sequences/gc_content_first_position.py
biokit/services/coding_sequences/gc_content_second_position.py
biokit/services/coding_sequences/gc_content_third_position.py
biokit/services/coding_sequences/gene_wise_relative_synonymous_codon_usage.py
biokit/services/coding_sequences/relative_synonymous_codon_usage.py
biokit/services/coding_sequences/translate_sequence.py
biokit/services/fastq/__init__.py
biokit/services/fastq/base.py
biokit/services/fastq/fastq_read_lengths.py
biokit/services/fastq/subset_pe_fastq_reads.py
biokit/services/fastq/subset_se_fastq_reads.py
jlsteenwyk_biokit-1.1.3.dist-info/LICENSE.md
jlsteenwyk_biokit-1.1.3.dist-info/METADATA
jlsteenwyk_biokit-1.1.3.dist-info/WHEEL
jlsteenwyk_biokit-1.1.3.dist-info/entry_points.txt
jlsteenwyk_biokit-1.1.3.dist-info/top_level.txt
jlsteenwyk_biokit-1.1.3.dist-info/RECORD
