Metadata-Version: 2.1
Name: jlsteenwyk-biokit
Version: 1.1.3
Summary: UNKNOWN
Home-page: https://github.com/jlsteenwyk/biokit
Author: Jacob L. Steenwyk
Author-email: jlsteenwyk@gmail.com
License: UNKNOWN
Platform: UNKNOWN
Classifier: Operating System :: OS Independent
Classifier: Intended Audience :: Science/Research
Classifier: Programming Language :: Python
Classifier: Programming Language :: Python :: 3.9
Classifier: Programming Language :: Python :: 3.10
Classifier: Programming Language :: Python :: 3.11
Classifier: Topic :: Scientific/Engineering
License-File: LICENSE.md
Requires-Dist: biopython >=1.82
Requires-Dist: numpy >=1.24.0
Requires-Dist: cython
